ql_kernel/__init__.py
ql_kernel/__main__.py
ql_kernel/analyzer.py
ql_kernel/context.py
ql_kernel/debug_info.py
ql_kernel/kimi.py
ql_kernel/prompt_template.py
ql_kernel-0.0.2.dist-info/LICENSE
ql_kernel-0.0.2.dist-info/METADATA
ql_kernel-0.0.2.dist-info/WHEEL
ql_kernel-0.0.2.dist-info/top_level.txt
ql_kernel-0.0.2.dist-info/RECORD
