Metadata-Version: 2.1
Name: ql_kernel
Version: 0.0.2
Summary: A kernel for jupyter to analysis data with AI support
Author-email: zhi4 <weatheringhzl@sina.com>
Maintainer-email: zhi4 <weatheringhzl@sina.com>
License: MIT License
Keywords: ai,jupyter,data,analysis
Requires-Python: >=3.10
License-File: LICENSE
